{
    "description": "暗黑2装备图鉴收集小程序",
    "packOptions": {
        "ignore": [],
        "include": []
    },
    "setting": {
        "bundle": false,
        "userConfirmedBundleSwitch": false,
        "urlCheck": false,
        "scopeDataCheck": false,
        "coverView": true,
        "es6": true,
        "postcss": true,
        "compileHotReLoad": false,
        "lazyloadPlaceholderEnable": false,
        "preloadBackgroundData": false,
        "minified": true,
        "autoAudits": false,
        "newFeature": false,
        "uglifyFileName": false,
        "uploadWithSourceMap": true,
        "useIsolateContext": true,
        "nodeModules": false,
        "enhance": true,
        "useMultiFrameRuntime": true,
        "useApiHook": true,
        "useApiHostProcess": true,
        "showShadowRootInWxmlPanel": true,
        "packNpmManually": false,
        "enableEngineNative": false,
        "packNpmRelationList": [],
        "showES6CompileOption": false,
        "minifyWXSS": true,
        "babelSetting": {
            "ignore": [],
            "disablePlugins": [],
            "outputPath": ""
        },
        "compileWorklet": false,
        "minifyWXML": true,
        "localPlugins": false,
        "disableUseStrict": false,
        "useCompilerPlugins": false,
        "condition": false,
        "swc": false,
        "disableSWC": true
    },
    "compileType": "miniprogram",
    "libVersion": "2.19.4",
    "appid": "wx44d7a51d6746d07c",
    "projectname": "d2-collection",
    "isGameTourist": false,
    "cloudfunctionRoot": "cloudfunctions/",
    "condition": {
        "search": {
            "list": []
        },
        "conversation": {
            "list": []
        },
        "game": {
            "list": []
        },
        "plugin": {
            "list": []
        },
        "gamePlugin": {
            "list": []
        },
        "miniprogram": {
            "list": []
        }
    },
    "simulatorPluginLibVersion": {},
    "editorSetting": {},
    "cloudfunctionTemplateRoot": "cloudfunctionTemplate/"
}